hsntools/__init__.py
hsntools/version.py
hsntools/io/__init__.py
hsntools/io/collections.py
hsntools/io/custom.py
hsntools/io/files.py
hsntools/io/h5.py
hsntools/io/nsp.py
hsntools/io/nwb.py
hsntools/io/sorting.py
hsntools/io/utils.py
hsntools/modutils/__init__.py
hsntools/modutils/dependencies.py
hsntools/objects/__init__.py
hsntools/objects/electrodes.py
hsntools/objects/task.py
hsntools/paths/__init__.py
hsntools/paths/create.py
hsntools/paths/defaults.py
hsntools/paths/paths.py
hsntools/plts/__init__.py
hsntools/plts/timestamps.py
hsntools/plts/utils.py
hsntools/run/__init__.py
hsntools/run/errors.py
hsntools/run/log.py
hsntools/sorting/__init__.py
hsntools/sorting/process.py
hsntools/sorting/utils.py
hsntools/tests/__init__.py
hsntools/tests/conftest.py
hsntools/tests/tsettings.py
hsntools/tests/tutils.py
hsntools/tests/io/__init__.py
hsntools/tests/io/test_collections.py
hsntools/tests/io/test_custom.py
hsntools/tests/io/test_files.py
hsntools/tests/io/test_h5.py
hsntools/tests/io/test_nsp.py
hsntools/tests/io/test_nwb.py
hsntools/tests/io/test_sorting.py
hsntools/tests/io/test_utils.py
hsntools/tests/modutils/__init__.py
hsntools/tests/modutils/dependencies.py
hsntools/tests/objects/__init__.py
hsntools/tests/objects/test_electrodes.py
hsntools/tests/objects/test_task.py
hsntools/tests/paths/__init__.py
hsntools/tests/paths/test_create.py
hsntools/tests/paths/test_paths.py
hsntools/tests/plts/__init__.py
hsntools/tests/plts/test_timestamps.py
hsntools/tests/plts/test_utils.py
hsntools/tests/run/__init__.py
hsntools/tests/run/test_errors.py
hsntools/tests/run/test_log.py
hsntools/tests/timestamps/__init__.py
hsntools/tests/timestamps/test_align.py
hsntools/tests/timestamps/test_dates.py
hsntools/tests/timestamps/test_peaks.py
hsntools/tests/timestamps/test_update.py
hsntools/tests/timestamps/test_utils.py
hsntools/tests/utils/__init__.py
hsntools/tests/utils/test_checks.py
hsntools/tests/utils/test_convert.py
hsntools/tests/utils/test_extract.py
hsntools-1.0.0.dist-info/LICENSE
hsntools-1.0.0.dist-info/METADATA
hsntools-1.0.0.dist-info/WHEEL
hsntools-1.0.0.dist-info/top_level.txt
hsntools-1.0.0.dist-info/RECORD
