Metadata-Version: 2.1
Name: hsntools
Version: 1.0.0
Summary: Code for working with the Human Single-Neuron Pipeline.
Download-URL: https://github.com/HSNPipeline/hsntools/releases
License: MIT License
Project-URL: Documentation, https://hsnpipeline.github.io/hsntools/
Project-URL: Bug Reports, https://github.com/HSNPipeline/hsntools/issues
Project-URL: Source, https://github.com/HSNPipeline/hsntools
Keywords: neuroscience,single units,data management,neurodata without borders
Platform: any
Classifier: Development Status :: 5 - Production/Stable
Classifier: Intended Audience :: Science/Research
Classifier: Topic :: Scientific/Engineering
Classifier: License :: OSI Approved :: MIT License
Classifier: Operating System :: Microsoft :: Windows
Classifier: Operating System :: MacOS
Classifier: Operating System :: POSIX
Classifier: Operating System :: Unix
Classifier: Programming Language :: Python
Classifier: Programming Language :: Python :: 3.7
Classifier: Programming Language :: Python :: 3.8
Classifier: Programming Language :: Python :: 3.9
Classifier: Programming Language :: Python :: 3.10
Classifier: Programming Language :: Python :: 3.11
Classifier: Programming Language :: Python :: 3.12
Classifier: Programming Language :: Python :: 3.13
Classifier: Programming Language :: Python :: 3.14
Requires-Python: >=3.7
License-File: LICENSE
Requires-Dist: numpy
Requires-Dist: pyyaml
Provides-Extra: all
Requires-Dist: matplotlib; extra == "all"
Requires-Dist: scipy; extra == "all"
Requires-Dist: scikit-learn; extra == "all"
Requires-Dist: pandas; extra == "all"
Requires-Dist: h5py; extra == "all"
Requires-Dist: pynwb; extra == "all"
Requires-Dist: neo; extra == "all"
Requires-Dist: mat73; extra == "all"
Requires-Dist: pytest; extra == "all"
Provides-Extra: files
Requires-Dist: scipy; extra == "files"
Requires-Dist: pandas; extra == "files"
Requires-Dist: h5py; extra == "files"
Requires-Dist: pynwb; extra == "files"
Requires-Dist: neo; extra == "files"
Requires-Dist: mat73; extra == "files"
Provides-Extra: nwb
Requires-Dist: h5py; extra == "nwb"
Requires-Dist: pynwb; extra == "nwb"
Provides-Extra: plot
Requires-Dist: matplotlib; extra == "plot"
Provides-Extra: tests
Requires-Dist: pytest; extra == "tests"
Provides-Extra: timestamps
Requires-Dist: scipy; extra == "timestamps"
Requires-Dist: scikit-learn; extra == "timestamps"
